cad_pyrx-2.2.41.5071.dist-info/licenses/LICENSE.txt
pyrx/PyAp.pyi
pyrx/PyAx.pyi
pyrx/PyBr.pyi
pyrx/PyBrx.pyi
pyrx/PyBrxBim.pyi
pyrx/PyBrxCv.pyi
pyrx/PyDb.pyi
pyrx/PyEd.pyi
pyrx/PyGe.pyi
pyrx/PyGi.pyi
pyrx/PyGs.pyi
pyrx/PyPl.pyi
pyrx/PyRx.pyi
pyrx/PyRx24.0.arx
pyrx/PyRx24.1.arx
pyrx/PyRx24.2.arx
pyrx/PyRx24.3.arx
pyrx/PyRx25.0.arx
pyrx/PyRx25.1.arx
pyrx/PyRx26.0.arx
pyrx/PyRxDebug.py
pyrx/PyRxG24.0.grx
pyrx/PyRxG25.0.grx
pyrx/PyRxG26.0.grx
pyrx/PyRxV24.0.brx
pyrx/PyRxV25.0.brx
pyrx/PyRxV26.0.brx
pyrx/PyRxZ24.0.zrx
pyrx/PyRxZ25.0.zrx
pyrx/PyRxZ26.0.zrx
pyrx/PySm.pyi
pyrx/RxLoader24.0.arx
pyrx/RxLoader24.1.arx
pyrx/RxLoader24.2.arx
pyrx/RxLoader24.3.arx
pyrx/RxLoader25.0.arx
pyrx/RxLoader25.1.arx
pyrx/RxLoader26.0.arx
pyrx/RxLoaderG24.0.grx
pyrx/RxLoaderG25.0.grx
pyrx/RxLoaderG26.0.grx
pyrx/RxLoaderV24.0.brx
pyrx/RxLoaderV25.0.brx
pyrx/RxLoaderV26.0.brx
pyrx/RxLoaderZ24.0.zrx
pyrx/RxLoaderZ25.0.zrx
pyrx/RxLoaderZ26.0.zrx
pyrx/__init__.py
pyrx/_commands.py
pyrx/_host_init.py
pyrx/commands.py
pyrx/config.py
pyrx/console.py
pyrx/pyrx_imp.py
pyrx/typing.py
pyrx/ap/__init__.py
pyrx/ap/utils.py
pyrx/db/__init__.py
pyrx/db/block.py
pyrx/db/block_reference.py
pyrx/db/database.py
pyrx/db/layout.py
pyrx/doc_utils/__init__.py
pyrx/doc_utils/boost_meta.py
pyrx/doc_utils/misc.py
pyrx/doc_utils/parse_docstring.py
pyrx/doc_utils/pyi_gen.py
pyrx/doc_utils/rx_meta.py
pyrx/doc_utils/stubs/PyAp.pyi
pyrx/doc_utils/stubs/PyDb.pyi
pyrx/doc_utils/stubs/__init__.py
pyrx/doc_utils/stubs/base.py
pyrx/ed/__init__.py
pyrx/ed/prompt.py
pyrx/ge/__init__.py
pyrx/ge/point.py
pyrx/repl/__init__.py
pyrx/repl/base.py
pyrx/repl/ptrepl.py
pyrx/repl/repl_cmds.py
pyrx/repl/stdlibrepl.py
pyrx/utils/__init__.py
pyrx/utils/decorators.py
pyrx/utils/reload.py
pyrx/utils/test_runner.py
pyrx/utils/wx.py
cad_pyrx-2.2.41.5071.dist-info/METADATA
cad_pyrx-2.2.41.5071.dist-info/WHEEL
cad_pyrx-2.2.41.5071.dist-info/top_level.txt
cad_pyrx-2.2.41.5071.dist-info/RECORD
