Metadata-Version: 2.4
Name: cad-pyrx
Version: 2.2.41.5071
Summary: Python for Autocad® and Clones.
Author-email: PyRx Dev Team <daniel@cadext.com>
License:                   GNU LESSER GENERAL PUBLIC LICENSE
Project-URL: Homepage, https://pyarx.blogspot.com/
Project-URL: Repository, https://github.com/CEXT-Dan/PyRx
Project-URL: Issues, https://github.com/CEXT-Dan/PyRx/issues
Keywords: AutoCAD,BricsCAD,GStarCAD,ZwCAD,CAD,dwg,dxf,Python,Wrappers,ARX,BRX,GRX,ZRX
Classifier: Development Status :: 5 - Production/Stable
Classifier: Intended Audience :: Developers
Classifier: Topic :: Software Development :: Libraries :: Python Modules
Classifier: License :: OSI Approved :: GNU Lesser General Public License v3 (LGPLv3)
Classifier: Programming Language :: Python :: 3.12
Classifier: Programming Language :: Python :: Implementation :: CPython
Classifier: Operating System :: Microsoft :: Windows
Requires-Python: <3.13.0,>=3.12.0
License-File: LICENSE.txt
Requires-Dist: wxpython>=4.2.3; os_name == "nt"
Requires-Dist: pywin32; os_name == "nt"
Requires-Dist: debugpy>=1.8.0
Requires-Dist: pydantic_settings
Provides-Extra: dev
Requires-Dist: pytest; extra == "dev"
Requires-Dist: build; extra == "dev"
Requires-Dist: ruff; extra == "dev"
Requires-Dist: python-dotenv[cli]; extra == "dev"
Requires-Dist: pre-commit; extra == "dev"
Requires-Dist: mypy; extra == "dev"
Requires-Dist: types-pywin32; extra == "dev"
Requires-Dist: asttokens; extra == "dev"
Requires-Dist: setuptools-scm>=8; extra == "dev"
Provides-Extra: ptrepl
Requires-Dist: ptpython; extra == "ptrepl"
Requires-Dist: prompt_toolkit; extra == "ptrepl"
Dynamic: license-file
